vfxtest.py
vfxtest-0.2.2.dist-info/LICENSE.txt
vfxtest-0.2.2.dist-info/METADATA
vfxtest-0.2.2.dist-info/WHEEL
vfxtest-0.2.2.dist-info/entry_points.txt
vfxtest-0.2.2.dist-info/top_level.txt
vfxtest-0.2.2.dist-info/RECORD
