Metadata-Version: 2.1
Name: vfxtest
Version: 0.2.2
Summary: Manages a test suite across multiple python contexts commonly found in a VFX production environment
Home-page: https://github.com/martin-chatterjee/vfxtest
Author: Martin Chatterjee
Author-email: martin@chatterjee.de
License: MIT
Project-URL: Documentation, https://vfxtest.readthedocs.org
Project-URL: Source, https://github.com/martin-chatterjee/vfxtest
Project-URL: Issues, https://github.com/martin-chatterjee/vfxtest/issues
Keywords: unittest coverage tdd test driven development dcc vfx 3d animation pipeline nuke houdini hython maya mayapy nuke
Classifier: Development Status :: 3 - Alpha
Classifier: License :: OSI Approved :: MIT License
Classifier: Intended Audience :: Developers
Classifier: Operating System :: Microsoft :: Windows
Classifier: Operating System :: POSIX :: Linux
Classifier: Programming Language :: Python
Classifier: Programming Language :: Python :: 2
Classifier: Programming Language :: Python :: 2.7
Classifier: Programming Language :: Python :: 3
Classifier: Programming Language :: Python :: 3.7
Classifier: Topic :: Software Development :: Quality Assurance
Classifier: Topic :: Software Development :: Testing
Requires-Python: >=2.7, !=3.0.*, !=3.1.*, !=3.2.*, !=3.3.*, !=3.4.*, !=3.5.*, !=3.6.*, <4
License-File: LICENSE.txt
Requires-Dist: virtualenv
Requires-Dist: coverage (>=4.5)
Requires-Dist: six
Requires-Dist: mock (>=3.0) ; python_version < "3.3"
